logger_local/SendToLogzIo.py
logger_local/__init__.py
logger_local/component.py
logger_local/connector_logger.py
logger_local/constants_src_logger_local.py
logger_local/debug_mode.py
logger_local/logger_component_enum.py
logger_local/logger_fields.py
logger_local/logger_local.py
logger_local/logger_output_enum.py
logger_local/message_severity.py
logger_local/meta_logger.py
logger_local/send_to_logzIo.py
logger_local/writer.py
logger_local-0.0.180.post2614.dist-info/licenses/LICENSE
logger_local-0.0.180.post2614.dist-info/METADATA
logger_local-0.0.180.post2614.dist-info/WHEEL
logger_local-0.0.180.post2614.dist-info/top_level.txt
logger_local-0.0.180.post2614.dist-info/RECORD
