Metadata-Version: 2.4
Name: logger-local
Version: 0.0.180.post2614
Summary: PyPI Package for Circles Logger Python Local
Home-page: https://github.com/circles-zone/logger-local-python-package
Author: Circles
Author-email: info@circlez.ai
Classifier: Programming Language :: Python :: 3
Classifier: Operating System :: OS Independent
License-File: LICENSE
Requires-Dist: mysql-connector-python>=8.5.0
Requires-Dist: logzio-python-handler>=4.1.2
Requires-Dist: user-context-remote>=0.0.21
Requires-Dist: python-sdk-remote>=0.0.149
Dynamic: author
Dynamic: author-email
Dynamic: classifier
Dynamic: description
Dynamic: description-content-type
Dynamic: home-page
Dynamic: license-file
Dynamic: requires-dist
Dynamic: summary
